README
setup.py
digress/__init__.py
digress/cli.py
digress/comparers.py
digress/constants.py
digress/errors.py
digress/testing.py
digress.egg-info/PKG-INFO
digress.egg-info/SOURCES.txt
digress.egg-info/dependency_links.txt
digress.egg-info/top_level.txt
digress/scm/__init__.py
digress/scm/dummy.py
digress/scm/git.py