Metadata-Version: 1.0
Name: digress
Version: 0.2
Summary: Python Regression Testing Suite
Home-page: UNKNOWN
Author: Tony Young
Author-email: rofflwaffls@gmail.com
License: UNKNOWN
Platform: UNKNOWN
